aek_auto_mlbuilder/__init__.py
aek_auto_mlbuilder/agglomerative.py
aek_auto_mlbuilder/base.py
aek_auto_mlbuilder/bayesian_ridge.py
aek_auto_mlbuilder/dbscan.py
aek_auto_mlbuilder/decision_tree.py
aek_auto_mlbuilder/elastic_net.py
aek_auto_mlbuilder/kmeans.py
aek_auto_mlbuilder/knn.py
aek_auto_mlbuilder/lasso_regression.py
aek_auto_mlbuilder/linear_regression.py
aek_auto_mlbuilder/logistic_regression.py
aek_auto_mlbuilder/naive_bayes.py
aek_auto_mlbuilder/nusvc.py
aek_auto_mlbuilder/perceptron.py
aek_auto_mlbuilder/random_forest.py
aek_auto_mlbuilder/rigde_regression.py
aek_auto_mlbuilder/svm.py
aek_auto_mlbuilder/utils.py
aek_auto_mlbuilder-0.16.1.dist-info/licenses/LICENSE
aek_auto_mlbuilder-0.16.1.dist-info/METADATA
aek_auto_mlbuilder-0.16.1.dist-info/WHEEL
aek_auto_mlbuilder-0.16.1.dist-info/top_level.txt
aek_auto_mlbuilder-0.16.1.dist-info/RECORD
