Metadata-Version: 2.4
Name: aek-auto-mlbuilder
Version: 0.16.1
Summary: Automatic ML model builder in Python
Home-page: https://github.com/alpemre8/aek-auto-mlbuilder
Author: Alp Emre Karaahmet
Author-email: alpemrekaraahmet@gmail.com
License: MIT
Requires-Python: >=3.8
License-File: LICENSE
Requires-Dist: scikit-learn>=1.0
Requires-Dist: numpy>=1.23
Requires-Dist: pandas>=1.5
Dynamic: author
Dynamic: author-email
Dynamic: description
Dynamic: description-content-type
Dynamic: home-page
Dynamic: license
Dynamic: license-file
Dynamic: requires-dist
Dynamic: requires-python
Dynamic: summary
